{
  "tracks": [
    {
      "id": "unknown-28-30",
      "title": "Unknown Track",
      "artist": "Unknown",
      "timestamp_appearances": [
        {"set_id": "chaos-in-the-cbd-ballantines-lebanon", "timestamp": "28:30"}
      ],
      "played_by": ["chaos-in-the-cbd"],
      "status": "unidentified",
      "request_count": 5
    },
    {
      "id": "unknown-37-50",
      "title": "Unknown Track",
      "artist": "Unknown",
      "timestamp_appearances": [
        {"set_id": "chaos-in-the-cbd-ballantines-lebanon", "timestamp": "37:50"}
      ],
      "played_by": ["chaos-in-the-cbd"],
      "status": "unidentified",
      "request_count": 4
    },
    {
      "id": "unknown-18-58",
      "title": "Unknown Track",
      "artist": "Unknown",
      "timestamp_appearances": [
        {"set_id": "chaos-in-the-cbd-ballantines-lebanon", "timestamp": "18:58"}
      ],
      "played_by": ["chaos-in-the-cbd"],
      "status": "unidentified",
      "request_count": 3
    }
  ],
  "stats": {
    "total_tracks": 3,
    "unidentified": 3,
    "confirmed": 0,
    "most_requested": "unknown-28-30"
  }
}
